{
  "timestamp": "2026-03-04T12:01:47.115401",
  "ubicacion": "Ribera d'Ebre",
  "url": "https://www.idealista.com/venta-viviendas/tarragona/ribera-d-ebre/?ordenado-por=fecha-publicacion-desc",
  "total": 59,
  "viviendas": [
    {
      "titulo": "Finca rústica en C-233, s/n, Flix",
      "precio": "105.000€",
      "ubicacion": "s/n, Flix",
      "habitaciones": "3 hab.",
      "metros": "112 m²",
      "url": "https://www.idealista.com/inmueble/110788788/",
      "descripcion": "Finca con casa en una posición elevada con vistas panorámicas a valles suaves, olivares y colinas lejanas. Se accede a la propiedad por un camino privado desde un sendero bien mantenido que sale de la carretera hacia el pueblo, donde el río Ebro serpentea hacia el mar. Ofrece un entorno rural tranquilo, a solo diez min",
      "anunciante": "Particular",
      "fecha_scraping": "2026-03-04T12:01:47.114882",
      "portal": "Idealista",
      "telefono": null
    },
    {
      "titulo": "Chalet pareado en Calle Joan Segú, 12, Mora d'Ebre",
      "precio": "131.000€",
      "ubicacion": "12, Mora d'Ebre",
      "habitaciones": "3 hab.",
      "metros": "105 m²",
      "url": "https://www.idealista.com/inmueble/110655241/",
      "descripcion": "Se vende fantástica vivienda de 2 plantas en pleno corazón de Mora Debre, ubicada a pocos pasos de la plaza principal y rodeada de todos los comercios y servicios esenciales (supermercados, farmacia, bancos, cafeterías y más).\n Características principales:\nVivienda distribuida en dos plantas\nExcelente ubicación cén",
      "anunciante": "Particular",
      "fecha_scraping": "2026-02-18T11:33:38.472994",
      "portal": "Idealista",
      "telefono": "640 67 73 53"
    },
    {
      "titulo": "Chalet pareado en Calle Ribera d'Ebre, 15, Mora la Nova",
      "precio": "185.000€",
      "ubicacion": "15, Mora la Nova",
      "habitaciones": "2 hab.",
      "metros": "90 m²",
      "url": "https://www.idealista.com/inmueble/110528364/",
      "descripcion": "Casa de planta baja luminosa con patio delante y detrás. Totalmente reformada de alta calidad con nuevas instalaciones de luz y agua, paredes sólidas enyesadas (nada de pladur) suelos de barro natural, aislamiento de techo, suelo y paredes exteriores y placas solares. Ventanas de aluminio y doble cristal, suelo radiant",
      "anunciante": "Particular",
      "fecha_scraping": "2026-02-16T18:03:20.541949",
      "portal": "Idealista",
      "telefono": "643 35 43 42"
    },
    {
      "titulo": "Piso en Calle Doctor Borràs, 6 a, Mora d'Ebre",
      "precio": "88.000€",
      "ubicacion": "6 a, Mora d'Ebre",
      "habitaciones": "2 hab.",
      "metros": "69 m²",
      "url": "https://www.idealista.com/inmueble/110510473/",
      "descripcion": "Piso luminoso con 2 plazas de garaje en Mora d’Ebre – listo para entrar a vivir\nUbicación:\n- Mora d’Ebre\n- Excelente comunicación (entrada y salida del pueblo)\n- A 1 minuto de supermercados, farmacias, bancos y restaurantes\nCaracterísticas principales:\n- Piso muy luminoso\n- Balcón\n- 2 habitaciones de matrimoni",
      "anunciante": "Particular",
      "fecha_scraping": "2026-02-16T18:03:20.541975",
      "portal": "Idealista",
      "telefono": null
    },
    {
      "titulo": "Casa o chalet independiente en Calle del Torrent, 56, La Torre de l'Espanyol",
      "precio": "310.000€",
      "ubicacion": "56, La Torre de l'Espanyol",
      "habitaciones": "5 hab.",
      "metros": "320 m²",
      "url": "https://www.idealista.com/inmueble/90880711/",
      "descripcion": "Casa adosada moderna, de concepto abierto reformada completamente en el año 2020. Consta de 4 plantas de 80 mts2. Dos son vivienda. 1a planta consta de cocina-comedor abierta al salon tv, sala juegos, habitacion doble y baño completo. La 2a planta consta de un espacio abierto (despacho, sala lectura, gimnasio. ), una s",
      "anunciante": "Particular",
      "fecha_scraping": "2026-02-16T18:03:20.541991",
      "portal": "Idealista",
      "telefono": "653 81 00 89"
    },
    {
      "titulo": "Finca rústica en Poligono, 1 &amp;, Garcia",
      "precio": "70.000€",
      "ubicacion": "1 &amp;, Garcia",
      "habitaciones": "1 hab.",
      "metros": "10 m²",
      "url": "https://www.idealista.com/inmueble/110371117/",
      "descripcion": "Finca rústica con acceso al río Ebro muy bonita, masia para reformar tierra muy fértil.",
      "anunciante": "Particular",
      "fecha_scraping": "2026-02-16T18:03:20.542003",
      "portal": "Idealista",
      "telefono": "722 37 28 55"
    },
    {
      "titulo": "Casa o chalet independiente en Calle Esglesia, 18, Tivissa",
      "precio": "100.000€",
      "ubicacion": "18, Tivissa",
      "habitaciones": "4 hab.",
      "metros": "220 m²",
      "url": "https://www.idealista.com/inmueble/2113125/",
      "descripcion": "Es una casa de pueblo que se encuentra en Llaberia, una pedanía de Tivissa. Un pueblo de unas pocas casas y una iglesia Románica a 9 km de Pratdip. Es una casa de piedra del Siglo XVII reformada y modernizada. Tranquilidad total a 700 metros de altura al final de la carretera en el parque natural de Llaberia\nTiene elec",
      "anunciante": "Particular",
      "fecha_scraping": "2026-02-16T18:03:20.542013",
      "portal": "Idealista",
      "telefono": "619 25 49 67"
    },
    {
      "titulo": "Casa de pueblo en Calle Major, 22, Rasquera",
      "precio": "80.500€",
      "ubicacion": "22, Rasquera",
      "habitaciones": "6 hab.",
      "metros": "544 m²",
      "url": "https://www.idealista.com/inmueble/103809638/",
      "descripcion": "Acogedora casa situada en el corazón de Rasquera, un pueblo que destila tranquilidad. Confort moderno con detalles rústicos. Espacios amplios y luminosos.",
      "anunciante": "Particular",
      "fecha_scraping": "2026-02-16T18:03:20.542024",
      "portal": "Idealista",
      "telefono": null
    },
    {
      "titulo": "Casa rural en Camino Llorell, 56, Tivissa",
      "precio": "395.000€",
      "ubicacion": "56, Tivissa",
      "habitaciones": "4 hab.",
      "metros": "135 m²",
      "url": "https://www.idealista.com/inmueble/110249961/",
      "descripcion": "Antigua masía catalogada de piedra de dos plantas totalmente reformada y lista para entrar a vivir, en plena naturaleza y con preciosas vistas a la montaña, ubicada en l' Ametlla de Mar – Tivissa, a 10 minutos del Mercadona y 20 de las playas de L'Ametlla de Mar.\nSe halla en una parcela de 29.489 m2 de olivos, pinos",
      "anunciante": "Particular",
      "fecha_scraping": "2026-02-16T18:03:20.542044",
      "portal": "Idealista",
      "telefono": "680 43 33 47"
    },
    {
      "titulo": "Piso en Calle Major, 19, Flix",
      "precio": "35.000€",
      "ubicacion": "19, Flix",
      "habitaciones": "4 hab.",
      "metros": "81 m²",
      "url": "https://www.idealista.com/inmueble/102216705/",
      "descripcion": "Piso entresuelo a reformar en finca señorial rehabilitada en el centro de Flix, delante del ayuntamiento y con ventanas a la Plaça de l'Església.\nTiene 81m2 según catastro, de los cuales 5m2 corresponden a un pequeño trastero en la misma planta.\nConsta de 4 estancias: una grande exterior, una grande interior, una pequ",
      "anunciante": "Particular",
      "fecha_scraping": "2026-02-16T18:03:20.542056",
      "portal": "Idealista",
      "telefono": "665 49 09 78"
    },
    {
      "titulo": "Piso en Calle Major, 19, Flix",
      "precio": "75.000€",
      "ubicacion": "19, Flix",
      "habitaciones": "1 hab.",
      "metros": "183 m²",
      "url": "https://www.idealista.com/inmueble/102223895/",
      "descripcion": "Piso en finca señorial rehabilitada en el centro de Flix, delante del ayuntamiento.\nTiene 183m2 según catastro, de los cuales 32m2 corresponden a un trastero con ventanas al exterior en la tercera planta, debajo de tejado (tipo buhardilla).\nEl piso consta de un espacio tipo loft totalmente reformado y amueblado de uno",
      "anunciante": "Particular",
      "fecha_scraping": "2026-02-16T18:03:20.542066",
      "portal": "Idealista",
      "telefono": "665 49 09 78"
    },
    {
      "titulo": "Piso en Calle Major, 7, Flix",
      "precio": "125.000€",
      "ubicacion": "7, Flix",
      "habitaciones": "3 hab.",
      "metros": "80 m²",
      "url": "https://www.idealista.com/inmueble/109715936/",
      "descripcion": "Piso de reciente construcción en Flix, municipio de Tarragona.\nBien comunicado por carretera con Tarragona, Barcelona, Valencia etc.\nTodos los servicios y transportes\nInmueble luminoso de\n3 habitaciones, dos dobles y una individual.\n1 baño\n1 aseo\nSalón comedor\nCocina independiente.\nEn definitiva una propiedad perfec",
      "anunciante": "Particular",
      "fecha_scraping": "2026-02-16T18:03:20.542077",
      "portal": "Idealista",
      "telefono": "673 05 48 79"
    },
    {
      "titulo": "Finca rústica en Poligono, 23, Ginestar",
      "precio": "120.000€",
      "ubicacion": "23, Ginestar",
      "habitaciones": "1 hab.",
      "metros": "70 m²",
      "url": "https://www.idealista.com/inmueble/108562782/",
      "descripcion": "Parcela rustica con nueva casa sin interior. Interior puede realizar su sueno. 4,5 ha con Olivos.",
      "anunciante": "Particular",
      "fecha_scraping": "2026-02-16T18:03:20.542088",
      "portal": "Idealista",
      "telefono": null
    },
    {
      "titulo": "Casa rural en Poligono, 23, Ginestar",
      "precio": "380.000€",
      "ubicacion": "23, Ginestar",
      "habitaciones": "3 hab.",
      "metros": "230 m²",
      "url": "https://www.idealista.com/inmueble/108562759/",
      "descripcion": "Amplia finca de 7 hectáreas ideal para caballos. ¡Permiso para 16 caballos disponible! Agua en toda la propiedad, amplias terrazas, parcialmente vallada. Opción de adquirir parcelas adicionales. Plantada de almendros y olivos. Magníficas vistas desde la casa de Ginestar y otros pueblos. El río Ebro está a pocos metros.",
      "anunciante": "Particular",
      "fecha_scraping": "2026-02-16T18:03:20.542099",
      "portal": "Idealista",
      "telefono": null
    },
    {
      "titulo": "Cortijo en Poligono 7 Parcela 36, 7, Miravet",
      "precio": "125.000€",
      "ubicacion": "7, Miravet",
      "habitaciones": "2 hab.",
      "metros": "125 m²",
      "url": "https://www.idealista.com/inmueble/107798247/",
      "descripcion": "Hermosa casa con 45000 m2 de almendros, olivos, algarrobos, higueras, etc… necesita ser terminada. Equipada con sistema solar de 5400 w incluyendo bat. iluminada. Generador, Watercubes de 6000 l con bomba de presión, calentador de agua eléctrico para ducha, cocina, etc. Cocina equipada.",
      "anunciante": "Particular",
      "fecha_scraping": "2026-02-16T18:03:20.542111",
      "portal": "Idealista",
      "telefono": "+32 497 19 24 00"
    },
    {
      "titulo": "Piso en Calle Doctor Borràs, 19, Mora d'Ebre",
      "precio": "110.000€",
      "ubicacion": "19, Mora d'Ebre",
      "habitaciones": "3 hab.",
      "metros": "90 m²",
      "url": "https://www.idealista.com/inmueble/109486388/",
      "descripcion": "Se vende piso en muy buen estado, 3hab. 2 baños, terraza, incluye plaza de parking, dentro del núcleo urbano. se incluyen muebles y electrodomésticos.",
      "anunciante": "Particular",
      "fecha_scraping": "2026-02-16T18:03:20.542122",
      "portal": "Idealista",
      "telefono": "696 02 71 27"
    },
    {
      "titulo": "Finca rústica en Lugar Mas Guinardera, 9107, Tivissa",
      "precio": "340.000€",
      "ubicacion": "9107, Tivissa",
      "habitaciones": "7 hab.",
      "metros": "300 m²",
      "url": "https://www.idealista.com/inmueble/109348263/",
      "descripcion": "Finca rustica situada a 10 km de l’Ametlla de mar\nRodeada ee 34 hectareas de olivos algarrobos y pinos\nTodas las comodidades\nPermiso para nucleo zoologico\nCasa principal, patios y varias dependencias legalizadas\nDepuradora y depositos de agua potable homologados\nReformada en 2017.",
      "anunciante": "Particular",
      "fecha_scraping": "2026-02-16T18:03:20.542132",
      "portal": "Idealista",
      "telefono": "630 02 37 47"
    },
    {
      "titulo": "Chalet pareado en Calle del Centre, 1, Garcia",
      "precio": "49.000€",
      "ubicacion": "1, Garcia",
      "habitaciones": "3 hab.",
      "metros": "95 m²",
      "url": "https://www.idealista.com/inmueble/84235900/",
      "descripcion": "se vende una casa de 90m2 de 3 plantas con mucha luminosidad, primera planta se compone de una cocina abierta sobre el comedor, segunda planta de 2 habitaciones dobles y de un baño, la tercera es un espacio abierto donde se podrían crear 2 grandes habitaciones. La casa esta al lado del rio Ebro y a solamente a 30km de",
      "anunciante": "Particular",
      "fecha_scraping": "2026-02-16T18:03:20.542144",
      "portal": "Idealista",
      "telefono": "699 61 49 02"
    },
    {
      "titulo": "Piso en Calle de Baix, 4, Flix",
      "precio": "69.500€",
      "ubicacion": "4, Flix",
      "habitaciones": "2 hab.",
      "metros": "70 m²",
      "url": "https://www.idealista.com/inmueble/39780650/",
      "descripcion": "Piso reformado que consta de dos habitaciones espaciosas, un salon comedor con balcon en vistas hacia el embalse de Flix, un baño, un trastero junto a una gran terraza. Bonito y muy acogedor. Ver sin compromiso previo aviso para concretar dia de la visita. Los muebles estan incluidos en el precio.\nPosibilidad de subrog",
      "anunciante": "Particular",
      "fecha_scraping": "2026-02-16T18:03:20.542154",
      "portal": "Idealista",
      "telefono": "661 27 30 70"
    },
    {
      "titulo": "Finca rústica en Calle del Portal, 3, La Torre de l'Espanyol",
      "precio": "265.000€",
      "ubicacion": "3, La Torre de l'Espanyol",
      "habitaciones": "5 hab.",
      "metros": "280 m²",
      "url": "https://www.idealista.com/inmueble/83878625/",
      "descripcion": "\"Gran finca rústica, situada a 5km de La Torre de l'Espanyol (Tarragona).\nLa finca consta de un terreno de 19.804 m. 2 y de una gran casa de 280m2 en dos plantas y de otra casa pequeña de campo de 70m2 también de 2 plantas.\nEl terreno esta plantumado con 1260 olivos (Arlequín, royal y terralte), algunos almendros y a",
      "anunciante": "Particular",
      "fecha_scraping": "2026-02-16T18:03:20.542164",
      "portal": "Idealista",
      "telefono": null
    },
    {
      "titulo": "Chalet adosado en Calle Comellarets, 15, Flix",
      "precio": "190.000€",
      "ubicacion": "15, Flix",
      "habitaciones": "5 hab.",
      "metros": "183 m²",
      "url": "https://www.idealista.com/inmueble/109070189/",
      "descripcion": "La casa adosada de Flix te ofrece el espacio y el entorno para una vida familiar cómoda o fines de semana con amigos. En una calle tranquila bordeada de árboles en el borde de Flix, estás cerca del río Ebro, con escuelas, tiendas y servicios locales todos a un fácil alcance.\nEn el interior, cinco dormitorios dobles, d",
      "anunciante": "Particular",
      "fecha_scraping": "2026-02-16T18:03:20.542174",
      "portal": "Idealista",
      "telefono": null
    },
    {
      "titulo": "Masía en flix, s/n, Flix",
      "precio": "260.000€",
      "ubicacion": "s/n, Flix",
      "habitaciones": "2 hab.",
      "metros": "160 m²",
      "url": "https://www.idealista.com/inmueble/98050568/",
      "descripcion": "Bungalow en venta en Flix, Riba-roja d'Ebre, Tarragona\nPrecioso Bungalow con 2 x Hectáreas de terreno a tan solo 9 minutos en coche del pueblo, supermercados, concesionarios, veterinarios, centro de salud, pubs, restaurantes y más.\nPiscina de 18.000 litros y cerca de la piscina caseta propia para guardar la bomba de",
      "anunciante": "Particular",
      "fecha_scraping": "2026-02-16T18:03:20.542186",
      "portal": "Idealista",
      "telefono": null
    },
    {
      "titulo": "Finca rústica en poligono 12 parcela 117, s/n, Garcia",
      "precio": "10.000€",
      "ubicacion": "s/n, Garcia",
      "habitaciones": "1 hab.",
      "metros": "5.631 m²",
      "url": "https://www.idealista.com/inmueble/108875532/",
      "descripcion": "En venta finca rústica de 5.631m2 de superficie según catastro.\nSe encuentra ubicada en el término municipal de \"Les Moles\" en el pueblo de Garcia, Tarragona.\nFinca totalmente llana.\nCuenta con agua y árboles de olivos con una superficie de 2.789m2\ny almendras con una superficie de 2.842m2.\nConsta también con un gallin",
      "anunciante": "Particular",
      "fecha_scraping": "2026-02-16T18:03:20.542196",
      "portal": "Idealista",
      "telefono": null
    },
    {
      "titulo": "Casa o chalet independiente en La barca, 2, Flix",
      "precio": "176.000€",
      "ubicacion": "2, Flix",
      "habitaciones": "3 hab.",
      "metros": "120 m²",
      "url": "https://www.idealista.com/inmueble/108836618/",
      "descripcion": "Bomba de calor, cocina vitrocerámica.",
      "anunciante": "Particular",
      "fecha_scraping": "2026-02-16T18:03:20.542206",
      "portal": "Idealista",
      "telefono": "656 33 86 42"
    },
    {
      "titulo": "Casa de pueblo en Calle de la Creu, 8, Benissanet",
      "precio": "50.000€",
      "ubicacion": "8, Benissanet",
      "habitaciones": "3 hab.",
      "metros": "320 m²",
      "url": "https://www.idealista.com/inmueble/108560792/",
      "descripcion": "Se vende fantástica casa de pueblo para reformar.\nDispone de 4 plantas divididas en Bodega, planta baja, 2 plantas y buhardilla.\nEl tejado es completamente nuevo y se pueden aprovechar los cimientos / estructura.\nLa casa está para actualizar, actualmente no tiene las estancias divididas.\nMuchas posibilidades, mejor",
      "anunciante": "Particular",
      "fecha_scraping": "2026-02-16T18:03:20.542217",
      "portal": "Idealista",
      "telefono": "607 18 29 80"
    },
    {
      "titulo": "Casa o chalet independiente en Avenida de les Aubagues, 24, Vinebre",
      "precio": "210.000€",
      "ubicacion": "24, Vinebre",
      "habitaciones": "5 hab.",
      "metros": "240 m²",
      "url": "https://www.idealista.com/inmueble/108110831/",
      "descripcion": "Preciosa casa de 240 m2 de dos plantas, ubicada en la zona de Ribera d’Ebre, en una finca con una hectárea y con olivos.\nEn la planta principal:\nDos baños con ducha (uno con mampara).\nDos habitaciones dobles y un individual.\nCocina con despensa y lavadero.\nGran comedor con chimenea y un porche.\nPlanta superior:\nUn b",
      "anunciante": "Particular",
      "fecha_scraping": "2026-02-16T18:03:20.542227",
      "portal": "Idealista",
      "telefono": "653 42 22 66"
    },
    {
      "titulo": "Piso en Pisos Santa Madrona, s/n, Riba-Roja d'Ebre",
      "precio": "41.000€",
      "ubicacion": "s/n, Riba-Roja d'Ebre",
      "habitaciones": "3 hab.",
      "metros": "77 m²",
      "url": "https://www.idealista.com/inmueble/37657996/",
      "descripcion": "VENTA DIRECTA DE PROPIETARIO\nEn venta piso de 77m2 construidos, situado en Riba Roja d'Ebre. Calle Baix Camp 5 3º1º.\nIDEAL PARA AFICIONADOS Y PROFESIONALES DE LA PESCA Y SEGUNDA RESIDENCIA.\nLa vivienda está situada en uno de los cinco bloques de vecinos en la Calle Baix Camp de Riba-roja d'Ebre, es un 3º1º sin ascenso",
      "anunciante": "Particular",
      "fecha_scraping": "2026-02-16T18:03:20.542239",
      "portal": "Idealista",
      "telefono": "676 07 75 59"
    },
    {
      "titulo": "Casa o chalet independiente en Calle del Mig, 23, Miravet",
      "precio": "55.000€",
      "ubicacion": "23, Miravet",
      "habitaciones": "8 hab.",
      "metros": "340 m²",
      "url": "https://www.idealista.com/inmueble/108029178/",
      "descripcion": "Casa en miravet, precisa de reforma, piso bajo reformado en 2010, casa construiida en el año 1900 con reformas en 1980.",
      "anunciante": "Particular",
      "fecha_scraping": "2026-02-16T18:03:20.542249",
      "portal": "Idealista",
      "telefono": "658 39 96 68"
    },
    {
      "titulo": "Casa o chalet independiente en urbanització ventonella, 6, Flix",
      "precio": "240.000€",
      "ubicacion": "6, Flix",
      "habitaciones": "5 hab.",
      "metros": "170 m²",
      "url": "https://www.idealista.com/inmueble/101096647/",
      "descripcion": "Casa de piedra 1000 metros cuadrados de parcela, zona muy tranquila pero se quemo su interior.",
      "anunciante": "Particular",
      "fecha_scraping": "2026-02-16T18:03:20.542260",
      "portal": "Idealista",
      "telefono": "628 55 58 33"
    },
    {
      "titulo": "Chalet adosado en Passatge del Roser, 11, Flix",
      "precio": "130.000€",
      "ubicacion": "11, Flix",
      "habitaciones": "4 hab.",
      "metros": "120 m²",
      "url": "https://www.idealista.com/inmueble/107342523/",
      "descripcion": "Adosado centrico - Obra nueva 2014 - Dos plantas -\nPrimera planta (Comedor- cocina - lavabo, despensa + patio i Trastero)\nSegunda planta: (4 habitaciones + 1 vestidor; Cuarto baño)\nCalefacción con Radiadores.",
      "anunciante": "Particular",
      "fecha_scraping": "2026-02-16T18:03:20.542270",
      "portal": "Idealista",
      "telefono": "626 52 97 41"
    },
    {
      "titulo": "Casa terrera en Camino de sequenes, 15 PolygonParcela, Mora la Nova",
      "precio": "199.000€",
      "ubicacion": "15 PolygonParcela, Mora la Nova",
      "habitaciones": "3 hab.",
      "metros": "155 m²",
      "url": "https://www.idealista.com/inmueble/101559283/",
      "descripcion": "Estufa de leña / calefacción central.",
      "anunciante": "Particular",
      "fecha_scraping": "2026-02-16T18:03:20.542281",
      "portal": "Idealista",
      "telefono": "610 32 45 50"
    },
    {
      "titulo": "Casa de pueblo en Calle Major de la Mata, 21, Tivissa",
      "precio": "35.000€",
      "ubicacion": "21, Tivissa",
      "habitaciones": "1 hab.",
      "metros": "65 m²",
      "url": "https://www.idealista.com/inmueble/106923585/",
      "descripcion": "En la Ribera de Ebro, en un paisaje que combina los bosques de montaña con el cultivo de viña, olivos y almendros, encontramos Darmos, un pequeño pueblo, pedanía de Tivissa, ocupado por cuatro bodegas pertenecientes a la prestigiosa DO Montsant.\nLa construcción, un almacén de 65m2 en planta baja en una parcela de 85m2",
      "anunciante": "Particular",
      "fecha_scraping": "2026-02-16T18:03:20.542292",
      "portal": "Idealista",
      "telefono": "609 98 52 49"
    },
    {
      "titulo": "Finca rústica en Calle la Fatarella, s/n, Riba-Roja d'Ebre",
      "precio": "325.000€",
      "ubicacion": "s/n, Riba-Roja d'Ebre",
      "habitaciones": "5 hab.",
      "metros": "300 m²",
      "url": "https://www.idealista.com/inmueble/38774742/",
      "descripcion": "",
      "anunciante": "Particular",
      "fecha_scraping": "2026-02-16T18:03:20.542302",
      "portal": "Idealista",
      "telefono": "605 60 83 75"
    },
    {
      "titulo": "Casa de pueblo en Calle de sant vicent, 4, Benissanet",
      "precio": "140.000€",
      "ubicacion": "4, Benissanet",
      "habitaciones": "3 hab.",
      "metros": "180 m²",
      "url": "https://www.idealista.com/inmueble/32542360/",
      "descripcion": "Casa pareada reformada, de 3 plantas, cada planta con baño completo. Dispone comedor-cocina (loft) 3 habitaciones dobles, bodega y trasteros, golfa de 50 mts2 transformada en sala de reuniones, amueblada y equipada. Pueblo de 1000 h. dispone de todos los servicios, comercios, restaurantes, piscina, polideportivo, trans",
      "anunciante": "Particular",
      "fecha_scraping": "2026-02-16T18:03:20.542313",
      "portal": "Idealista",
      "telefono": "687 31 49 80"
    },
    {
      "titulo": "Casa o chalet independiente en Calle Sant Antoni, 18, Riba-Roja d'Ebre",
      "precio": "395.000€",
      "ubicacion": "18, Riba-Roja d'Ebre",
      "habitaciones": "4 hab.",
      "metros": "245 m²",
      "url": "https://www.idealista.com/inmueble/86578919/",
      "descripcion": "Bien Echo Chalet, 4 x Dormitorios, 2 x Banos y un Aseo, Sala, Cocina x 2, Aire Condicionado, Calefacion Central de aceite, Lavadero, Despensar, Jardin, Balcon, Vallado, Puerto de Entrar.",
      "anunciante": "Particular",
      "fecha_scraping": "2026-02-16T18:03:20.542323",
      "portal": "Idealista",
      "telefono": "677 82 93 35"
    },
    {
      "titulo": "Finca rústica en C-12, s/n, Flix",
      "precio": "425.000€",
      "ubicacion": "s/n, Flix",
      "habitaciones": "7 hab.",
      "metros": "450 m²",
      "url": "https://www.idealista.com/inmueble/105806875/",
      "descripcion": "Se vende amueblado, con huerto, y parcela de olivos, almendros y árboles frutales, toda la maquinaria agrícola incluida en el precio.",
      "anunciante": "Particular",
      "fecha_scraping": "2026-02-16T18:03:20.542334",
      "portal": "Idealista",
      "telefono": null
    },
    {
      "titulo": "Finca rústica en Camino Vial, s/n, Mora la Nova",
      "precio": "109.000€",
      "ubicacion": "s/n, Mora la Nova",
      "habitaciones": "4 hab.",
      "metros": "130 m²",
      "url": "https://www.idealista.com/inmueble/105696516/",
      "descripcion": "Finca exclusiva junto al río Ebro en Móra la Nova (Tarragona)\nEn la tranquila ribera izquierda del Ebro, a un paso de la población de Móra la Nova, se encuentra esta finca de 7.000 m² que combina naturaleza, producción agrícola y un enorme potencial para desarrollar un proyecto personal o recreativo en un entorno únic",
      "anunciante": "Particular",
      "fecha_scraping": "2026-02-16T18:03:20.542344",
      "portal": "Idealista",
      "telefono": "627 76 75 01"
    },
    {
      "titulo": "Casa o chalet independiente en Calle de la Torna, 2, Garcia",
      "precio": "116.500€",
      "ubicacion": "2, Garcia",
      "habitaciones": "11 hab.",
      "metros": "294 m²",
      "url": "https://www.idealista.com/inmueble/40530121/",
      "descripcion": "Bonita casa de 11 habitaciones, 3 baños completos y totalmente reformada y equipada para entrar a vivir. Salón y cocina en una sala diáfana a dos alturas. Delante de la puerta hay una pequeña zona de aparcamiento para varios coches. Inmueble muy versátil ya que es ideal para una casa de turismo rural. Ideal para famili",
      "anunciante": "Particular",
      "fecha_scraping": "2026-02-16T18:03:20.542354",
      "portal": "Idealista",
      "telefono": "645 50 79 24"
    },
    {
      "titulo": "Casa o chalet independiente en Mora la Nova",
      "precio": "160.000€",
      "ubicacion": "",
      "habitaciones": "10 hab.",
      "metros": "391 m²",
      "url": "https://www.idealista.com/inmueble/96897647/",
      "descripcion": "IDEAL PARA INVERSOR. Posibilidad de financiar parte adquisición del edificio con subvención fondo de transición nuclear si se crea negocio. Municipio propuesto por Gobierno español para albergar importante inversión multimillonaria de Gigafactoria de inteligencia artificial.\nADEMÁS DE USO RESIDENCIAL, se puede destinar",
      "anunciante": "Particular",
      "fecha_scraping": "2026-02-16T18:03:20.542366",
      "portal": "Idealista",
      "telefono": "678 22 85 69"
    },
    {
      "titulo": "Casa de pueblo en Calle Abadia, 38, Asco",
      "precio": "17.130€",
      "ubicacion": "38, Asco",
      "habitaciones": null,
      "metros": "240 m²",
      "url": "https://www.idealista.com/inmueble/103487580/",
      "descripcion": "A reformar\nProyecto de casa + casa a reformar.",
      "anunciante": "Particular",
      "fecha_scraping": "2026-02-16T18:03:20.542377",
      "portal": "Idealista",
      "telefono": "616 56 93 66"
    },
    {
      "titulo": "Casa de pueblo en 2ª Travessia la Palla, 2, Riba-Roja d'Ebre",
      "precio": "55.000€",
      "ubicacion": "2, Riba-Roja d'Ebre",
      "habitaciones": "15 hab.",
      "metros": "650 m²",
      "url": "https://www.idealista.com/inmueble/103072368/",
      "descripcion": "Gran casa centenaria de pueblo con patio soleado y elementos propios de las labores agrícolas. A reformar completamente para distribución interior a conveniencia. Posibilidad de ampliar espacio y construir terraza. Ideal para segunda residencia o para negocios como casa rural, casa de colonias, restaurante...",
      "anunciante": "Particular",
      "fecha_scraping": "2026-02-16T18:03:20.542389",
      "portal": "Idealista",
      "telefono": "649 97 71 64"
    },
    {
      "titulo": "Casa rural en Rustic Country House, 1, Rasquera",
      "precio": "425.000€",
      "ubicacion": "1, Rasquera",
      "habitaciones": "3 hab.",
      "metros": "180 m²",
      "url": "https://www.idealista.com/inmueble/101891499/",
      "descripcion": "Situado en el Valle de Burga, a 45 minutos del aeropuerto de Reus y a 1,5 horas de Barcelona, se encuentra esta magnífica casa de campo.",
      "anunciante": "Particular",
      "fecha_scraping": "2026-02-16T18:03:20.542400",
      "portal": "Idealista",
      "telefono": "+44 7580 052056"
    },
    {
      "titulo": "Casa o chalet independiente en Plaza de la Verge, 4, Mora d'Ebre",
      "precio": "240.000€",
      "ubicacion": "4, Mora d'Ebre",
      "habitaciones": "8 hab.",
      "metros": "1.000 m²",
      "url": "https://www.idealista.com/inmueble/29164547/",
      "descripcion": "Gran casa en el centro de Mora con un maravilloso jardín interior. Posibilidad de dividir en apartamentos independientes.",
      "anunciante": "Particular",
      "fecha_scraping": "2026-02-16T18:03:20.542411",
      "portal": "Idealista",
      "telefono": "619 45 86 76"
    },
    {
      "titulo": "Casa de pueblo en Raval de Santa Anna, 9, Garcia",
      "precio": "54.750€",
      "ubicacion": "9, Garcia",
      "habitaciones": "2 hab.",
      "metros": "75 m²",
      "url": "https://www.idealista.com/inmueble/97790964/",
      "descripcion": "Casa de pueblo tradicional con dos dormitorios y dos aseos, cocina, salón y trastero. Modernizado y en muy buen estado, y se vende completamente amueblado.",
      "anunciante": "Particular",
      "fecha_scraping": "2026-02-16T18:03:20.542422",
      "portal": "Idealista",
      "telefono": "+44 7768 277748"
    },
    {
      "titulo": "Finca rústica en Benisanet camino, s/n, Benissanet",
      "precio": "42.000€",
      "ubicacion": "s/n, Benissanet",
      "habitaciones": "1 hab.",
      "metros": "35 m²",
      "url": "https://www.idealista.com/inmueble/96451516/",
      "descripcion": "",
      "anunciante": "Particular",
      "fecha_scraping": "2026-02-16T18:03:20.542433",
      "portal": "Idealista",
      "telefono": "669 30 57 80"
    },
    {
      "titulo": "Casa de pueblo en Calle de l estació, s/n, Mora la Nova",
      "precio": "160.000€",
      "ubicacion": "s/n, Mora la Nova",
      "habitaciones": "5 hab.",
      "metros": "150 m²",
      "url": "https://www.idealista.com/inmueble/90656435/",
      "descripcion": "Casa de unos 150m2 y 10000m2de terreno con 270 olivos, 2 plantas, en la planta baja habitación suite con baño y comedor con cocina americana recién renovada totalmente nueva y en la planta superior 4 habitaciones y un baño, dispone de garaje para 2 coches, chimenea que proporciona la calefacción y dos aparatos de aire",
      "anunciante": "Particular",
      "fecha_scraping": "2026-02-16T18:03:20.542444",
      "portal": "Idealista",
      "telefono": "639 48 00 78"
    },
    {
      "titulo": "Piso en Avenida de la Llum, 17, Flix",
      "precio": "200.000€",
      "ubicacion": "17, Flix",
      "habitaciones": "4 hab.",
      "metros": "121 m²",
      "url": "https://www.idealista.com/inmueble/88246035/",
      "descripcion": "Fantástico piso en la villa de Flix. Se trata de un piso amplio y soleado en una finca construida en 2007 con vistas al río Ebro. El piso tiene tres habitaciones (2 dobles), 2 baños, 1 cuarto, cocina independiente, comedor y galería. La oferta viene acompañada de dos plazas de parking de 13,5 m2 y un trastero de 12,5 m",
      "anunciante": "Particular",
      "fecha_scraping": "2026-02-16T18:03:20.542454",
      "portal": "Idealista",
      "telefono": "605 37 70 99"
    },
    {
      "titulo": "Piso en Calle Gardènia, 1, Mora d'Ebre",
      "precio": "130.000€",
      "ubicacion": "1, Mora d'Ebre",
      "habitaciones": "3 hab.",
      "metros": "81 m²",
      "url": "https://www.idealista.com/inmueble/86685048/",
      "descripcion": "Dispone de la pre-instalación del aire acondicionado, 2 terrazas.",
      "anunciante": "Particular",
      "fecha_scraping": "2026-02-16T18:03:20.542464",
      "portal": "Idealista",
      "telefono": "686 42 34 83"
    },
    {
      "titulo": "Casa de pueblo en Raval de Santa Anna, 6, Garcia",
      "precio": "80.000€",
      "ubicacion": "6, Garcia",
      "habitaciones": "3 hab.",
      "metros": "160 m²",
      "url": "https://www.idealista.com/inmueble/36761929/",
      "descripcion": "SOLO VENTA. Casa en el centro del pueblo, no es nueva pero esta bien conservada. Tres habitaciones para colchones de 135+105+90 y 90 cm. Dispone garaje y lavadero. Tiene buhardilla diáfana con varias camas más en la última planta. Está lista para entrar a vivir.",
      "anunciante": "Particular",
      "fecha_scraping": "2026-02-16T18:03:20.542474",
      "portal": "Idealista",
      "telefono": "679 29 69 49"
    },
    {
      "titulo": "Casa de pueblo en Calle Portal, 5, Riba-Roja d'Ebre",
      "precio": "17.000€",
      "ubicacion": "5, Riba-Roja d'Ebre",
      "habitaciones": "6 hab.",
      "metros": "128 m²",
      "url": "https://www.idealista.com/inmueble/82560230/",
      "descripcion": "",
      "anunciante": "Particular",
      "fecha_scraping": "2026-02-16T18:03:20.542484",
      "portal": "Idealista",
      "telefono": "684 02 22 93"
    },
    {
      "titulo": "Casa de pueblo en Calle Hospital, 13, Asco",
      "precio": "30.000€",
      "ubicacion": "13, Asco",
      "habitaciones": "4 hab.",
      "metros": "180 m²",
      "url": "https://www.idealista.com/inmueble/81747446/",
      "descripcion": "Casa de 180m2 en el centro de Ascó, justo enfrente del ayuntamiento. Se ha cambiado el tejado por completo, así como todas las vigas que han sido necesarias para garantizar la firmeza de la casa a pesar de los años que tiene. Se ha hecho la fachada nueva, se ha pintado y se ha colocado canalización para que la recogida",
      "anunciante": "Particular",
      "fecha_scraping": "2026-02-16T18:03:20.542496",
      "portal": "Idealista",
      "telefono": "630 40 42 03"
    },
    {
      "titulo": "Caserón en Calle la Pena, 2, Riba-Roja d'Ebre",
      "precio": "85.000€",
      "ubicacion": "2, Riba-Roja d'Ebre",
      "habitaciones": "1 hab.",
      "metros": "590 m²",
      "url": "https://www.idealista.com/inmueble/37845327/",
      "descripcion": "Antiguo molino aceitero. Posibilidad d construir 3 plantas.\nIdeal para hotel, edifico apartamentos, centro de ancianos, etc, etc.\nMagníficas vistas al río Ebro.\nTranquilidad absoluta.",
      "anunciante": "Particular",
      "fecha_scraping": "2026-02-16T18:03:20.542506",
      "portal": "Idealista",
      "telefono": "649 59 19 83"
    },
    {
      "titulo": "Caserón en Calle la Pena, 2, Riba-Roja d'Ebre",
      "precio": "85.000€",
      "ubicacion": "2, Riba-Roja d'Ebre",
      "habitaciones": "1 hab.",
      "metros": "600 m²",
      "url": "https://www.idealista.com/inmueble/37845244/",
      "descripcion": "Antiguo molina aceitero. De 600 m2.\nPosibilidad de construir 3 plantas.\nBuenas opciones para bloque d viviendas, hotel, centro para ancianos, etc.\nMagníficas vistas al río Ebro y tranquilidad absoluta.",
      "anunciante": "Particular",
      "fecha_scraping": "2026-02-16T18:03:20.542517",
      "portal": "Idealista",
      "telefono": "649 59 19 83"
    },
    {
      "titulo": "Casa de pueblo en Calle Calvari, 10, Flix",
      "precio": "95.000€",
      "ubicacion": "10, Flix",
      "habitaciones": "9 hab.",
      "metros": "250 m²",
      "url": "https://www.idealista.com/inmueble/37621700/",
      "descripcion": "",
      "anunciante": "Particular",
      "fecha_scraping": "2026-02-16T18:03:20.542527",
      "portal": "Idealista",
      "telefono": "646 12 31 24"
    },
    {
      "titulo": "Casa o chalet independiente en de les Flors, 13, Miravet",
      "precio": "130.000€",
      "ubicacion": "13, Miravet",
      "habitaciones": "3 hab.",
      "metros": "152 m²",
      "url": "https://www.idealista.com/inmueble/25699686/",
      "descripcion": "Casa de pueblo de cuatro plantas totalmente reformada en 2005 integralmente (puertas baños instalaciones nuevas techos suelos etc). planta baja con almacen trastero, sala de máquinas-planta 1ª un aseo i salón comedor con cocina con barra americana abierta al salón-2ª planta 1 baño completo 1 habita de 30 m2 y 1 individ",
      "anunciante": "Particular",
      "fecha_scraping": "2026-02-16T18:03:20.542535",
      "portal": "Idealista",
      "telefono": "606 20 85 39"
    },
    {
      "titulo": "Ático en Calle consuelo zaragoza, 5, Mora d'Ebre",
      "precio": "99.000€",
      "ubicacion": "5, Mora d'Ebre",
      "habitaciones": "2 hab.",
      "metros": "85 m²",
      "url": "https://www.idealista.com/inmueble/31045401/",
      "descripcion": "Parquet, bomba calor y radiadores eléctricos, electrodomésticos nuevos, amoblado, recién pintado, terraza privada con muy buenas vistas del río Ebro.",
      "anunciante": "Particular",
      "fecha_scraping": "2026-02-16T18:03:20.542545",
      "portal": "Idealista",
      "telefono": "630 62 52 86"
    },
    {
      "titulo": "Casa o chalet independiente en Avenida de la llum, s/n, Flix",
      "precio": "200.000€",
      "ubicacion": "s/n, Flix",
      "habitaciones": "4 hab.",
      "metros": "121 m²",
      "url": "https://www.idealista.com/inmueble/30629735/",
      "descripcion": "Vivienda aislada en el casco urbano de Flix. Necesita algunas mejoras en instalaciones y carpintería. Posibilidad de hacer una piscina o una promoción de 5 o 6 viviendas adosadas de 170-200 m2 cada una. (edificabilidad total de 1238, 00 m2) Las infraestructuras urbanas están total y recientemente consolidades. Atractiv",
      "anunciante": "Particular",
      "fecha_scraping": "2026-02-16T18:03:20.542553",
      "portal": "Idealista",
      "telefono": "651 15 88 09"
    },
    {
      "titulo": "Casa de pueblo en Calle Mayor, 2, Flix",
      "precio": "160.000€",
      "ubicacion": "2, Flix",
      "habitaciones": "4 hab.",
      "metros": "171 m²",
      "url": "https://www.idealista.com/inmueble/25948294/",
      "descripcion": "SÓLO HASTA EL 31/12/17 (165.000€). Condiciones especiales de compra en tres años de alquiler, (Posteriormente volverá a su precio de 200.000€). Consultar directamente con compromiso de compra. Abstenerse curiosos no se facilita información telefónicamente.",
      "anunciante": "Particular",
      "fecha_scraping": "2026-02-16T18:03:20.542566",
      "portal": "Idealista",
      "telefono": "699 93 77 29"
    },
    {
      "titulo": "Casa o chalet independiente en Calle Comarques Catalanes, 10, Tivissa",
      "precio": "15.000€",
      "ubicacion": "10, Tivissa",
      "habitaciones": null,
      "metros": "100 m²",
      "url": "https://www.idealista.com/inmueble/1671914/",
      "descripcion": "Vivienda individual de 4 plantas a rehabilitar en el centro de La serra d´almos (tivissa) - tarragona\ndistribución:\nterraza descubierta de 20 m2.",
      "anunciante": "Particular",
      "fecha_scraping": "2026-02-16T18:03:20.542575",
      "portal": "Idealista",
      "telefono": "669 55 67 85"
    }
  ]
}